pobshell/__init__.py
pobshell/common.py
pobshell/dirops.py
pobshell/infocmds.py
pobshell/pob.py
pobshell/pob_inspect.py
pobshell/pob_unparse.py
pobshell/pobmain.py
pobshell/pobnode.py
pobshell/strpath.py
pobshell/user_defs.py
pobshell/manpages/Evaluation.txt
pobshell/manpages/LIMIT.txt
pobshell/manpages/TARGET.txt
pobshell/manpages/abcs.txt
pobshell/manpages/allow_style.txt
pobshell/manpages/auto_import.txt
pobshell/manpages/cat.txt
pobshell/manpages/cd.txt
pobshell/manpages/cdh.txt
pobshell/manpages/comment.txt
pobshell/manpages/die.txt
pobshell/manpages/doc.txt
pobshell/manpages/enumerate.txt
pobshell/manpages/eval.txt
pobshell/manpages/explain.txt
pobshell/manpages/filepath.txt
pobshell/manpages/find.txt
pobshell/manpages/global_ns.txt
pobshell/manpages/hide.txt
pobshell/manpages/id.txt
pobshell/manpages/introduction.txt
pobshell/manpages/ls.txt
pobshell/manpages/man.txt
pobshell/manpages/map.txt
pobshell/manpages/memsize.txt
pobshell/manpages/missing.txt
pobshell/manpages/module.txt
pobshell/manpages/mount.txt
pobshell/manpages/mro.txt
pobshell/manpages/noraise.txt
pobshell/manpages/null_separator.txt
pobshell/manpages/pathinfo.txt
pobshell/manpages/pprint.txt
pobshell/manpages/predicates.txt
pobshell/manpages/printpy.txt
pobshell/manpages/prune.txt
pobshell/manpages/pwd.txt
pobshell/manpages/py.txt
pobshell/manpages/pydoc.txt
pobshell/manpages/pypath.txt
pobshell/manpages/quiet.txt
pobshell/manpages/repr.txt
pobshell/manpages/revisit.txt
pobshell/manpages/rooteval.txt
pobshell/manpages/shell.txt
pobshell/manpages/show.txt
pobshell/manpages/signature.txt
pobshell/manpages/str.txt
pobshell/manpages/trace_frequency.txt
pobshell/manpages/tree.txt
pobshell/manpages/type.txt
pobshell/manpages/typename.txt
pobshell/manpages/which.txt
pobshell-0.2.0.dist-info/licenses/LICENSE
pobshell-0.2.0.dist-info/METADATA
pobshell-0.2.0.dist-info/WHEEL
pobshell-0.2.0.dist-info/top_level.txt
pobshell-0.2.0.dist-info/RECORD
