Metadata-Version: 2.4
Name: pobshell
Version: 0.2.0
Summary: A Bash-like shell for Python objects
Home-page: https://github.com/pdalloz/pobshell
Author: Peter Dalloz
Author-email: pdalloz@proton.me
License: MIT
Classifier: Programming Language :: Python :: 3
Classifier: Programming Language :: Python :: 3.12
Classifier: License :: OSI Approved :: MIT License
Classifier: Operating System :: MacOS :: MacOS X
Requires-Python: >=3.11,<4
License-File: LICENSE
Requires-Dist: cmd2<3.0,>=2.5.8
Requires-Dist: Pygments<3.0,>=2.15.1
Requires-Dist: Pympler<1.0,>=0.9
Requires-Dist: rich<15.0,>=13.0.0
Requires-Dist: six<2.0,>=1.16.0
Requires-Dist: pyreadline3; sys_platform == "win32"
Dynamic: author
Dynamic: author-email
Dynamic: classifier
Dynamic: description
Dynamic: description-content-type
Dynamic: home-page
Dynamic: license
Dynamic: license-file
Dynamic: requires-dist
Dynamic: requires-python
Dynamic: summary
